{
    "priceInfo": {
      "current": {
        "total": 0.3001,
        "energy": 0.1055,
        "tax": 0.1946,
        "startsAt": "2025-01-03T16:00:00.000+01:00"
      },
      "today": [
        {
          "total": 0.293,
          "energy": 0.0996,
          "tax": 0.1934,
          "startsAt": "2025-01-03T00:00:00.000+01:00"
        },
        {
          "total": 0.2787,
          "energy": 0.0875,
          "tax": 0.1912,
          "startsAt": "2025-01-03T01:00:00.000+01:00"
        }
      ],
      "tomorrow": [
        {
          "total": 0.2822,
          "energy": 0.0904,
          "tax": 0.1918,
          "startsAt": "2025-01-04T00:00:00.000+01:00"
        },
        {
          "total": 0.282,
          "energy": 0.0903,
          "tax": 0.1917,
          "startsAt": "2025-01-04T01:00:00.000+01:00"
        }
      ]
    }
  }